bambu/__init__.py
bambu/logo.py
bambu/download/__init__.py
bambu/models/__init__.py
bambu/models/decision_tree.py
bambu/models/gradient_boosting.py
bambu/models/logistic_regression.py
bambu/models/neural_network.py
bambu/models/svm.py
bambu/plots/__init__.py
bambu/predict/__init__.py
bambu/predict/run.py
bambu/preprocess/__init__.py
bambu/preprocess/preprocessors/__init__.py
bambu/preprocess/preprocessors/descriptors.py
bambu/preprocess/preprocessors/mol2vec.py
bambu/preprocess/preprocessors/morgan.py
bambu/train/__init__.py
bambu/validate/__init__.py
bambu_qsar-0.0.18.dist-info/METADATA
bambu_qsar-0.0.18.dist-info/WHEEL
bambu_qsar-0.0.18.dist-info/entry_points.txt
bambu_qsar-0.0.18.dist-info/top_level.txt
bambu_qsar-0.0.18.dist-info/RECORD
