Metadata-Version: 2.1
Name: bambu-qsar
Version: 0.0.18
Summary: bambu (bioassays model builder) is CLI tool to build QSAR models based on PubChem BioAssays datasets
Author: Isadora Leitzke Guidotti, Frederico Schmitt Kremer
Author-email: leitzke.gi@gmail.com, fred.s.kremer@gmail.com
Keywords: bioinformatics machine-learning data science drug discovery QSAR
Requires-Dist: pandas
Requires-Dist: numpy
Requires-Dist: scikit-learn
Requires-Dist: flaml (==1.0.0)
Requires-Dist: imbalanced-learn
Requires-Dist: requests
Requires-Dist: tqdm
Requires-Dist: lightgbm
Requires-Dist: retrying
Requires-Dist: gensim (==3.8.3)
